arifpaypython/__init__.py
arifpaypython/api.py
arifpaypython-0.1.2.dist-info/METADATA
arifpaypython-0.1.2.dist-info/WHEEL
arifpaypython-0.1.2.dist-info/top_level.txt
arifpaypython-0.1.2.dist-info/RECORD
