Metadata-Version: 2.1
Name: arifpaypython
Version: 0.1.2
Summary: arifpay-python is a Python package that provides a simple interface for integrating with the ArifPay payment gateway.
Author: Sina
Author-email: b99174794@gmail.com
Classifier: Programming Language :: Python :: 3
Classifier: License :: OSI Approved :: MIT License
Classifier: Operating System :: OS Independent
Requires-Python: >=3.7
Requires-Dist: aiohttp
